paws/__init__.py
paws/__main__.py
paws/cli.py
paws/helper/__init__.py
paws/helper/dataclasses.py
paws/helper/logging.py
victorykit_paws-0.0.1rc2.dist-info/LICENSE
victorykit_paws-0.0.1rc2.dist-info/METADATA
victorykit_paws-0.0.1rc2.dist-info/NOTICE.md
victorykit_paws-0.0.1rc2.dist-info/WHEEL
victorykit_paws-0.0.1rc2.dist-info/entry_points.txt
victorykit_paws-0.0.1rc2.dist-info/top_level.txt
victorykit_paws-0.0.1rc2.dist-info/zip-safe
victorykit_paws-0.0.1rc2.dist-info/RECORD
