Metadata-Version: 2.1
Name: victorykit-paws
Version: 0.0.1rc2
Summary: AWS CLI profile management utility
Home-page: https://victorykit.bitbucket.io/py-paws
Author: Tiara Rodney (victory-k.it)
Author-email: py-paws@victoryk.it
Project-URL: Bug Tracker, https://bitbucket.org/victorykit/py-paws
Classifier: Development Status :: 4 - Beta
Classifier: Environment :: Other Environment
Classifier: Intended Audience :: Developers
Classifier: Topic :: Utilities
Classifier: Topic :: Security
Classifier: Programming Language :: Python :: 3.7
Classifier: Programming Language :: Python :: 3.8
Classifier: Programming Language :: Python :: 3.9
Classifier: Programming Language :: Python :: 3.10
Classifier: Programming Language :: Python :: 3.11
Classifier: Operating System :: OS Independent
Classifier: License :: Other/Proprietary License
Requires-Python: >=3.7
License-File: LICENSE
License-File: NOTICE.md
Requires-Dist: botocore
